nonebot_plugin_randomtkk/__init__.py
nonebot_plugin_randomtkk/config.py
nonebot_plugin_randomtkk/handler.py
nonebot_plugin_randomtkk/resource/chika.png
nonebot_plugin_randomtkk/resource/chisato.png
nonebot_plugin_randomtkk/resource/dia.png
nonebot_plugin_randomtkk/resource/eli.png
nonebot_plugin_randomtkk/resource/hanamaru.png
nonebot_plugin_randomtkk/resource/hanayo.png
nonebot_plugin_randomtkk/resource/honoka.png
nonebot_plugin_randomtkk/resource/kanan.png
nonebot_plugin_randomtkk/resource/kanon.png
nonebot_plugin_randomtkk/resource/kotori.png
nonebot_plugin_randomtkk/resource/maki.png
nonebot_plugin_randomtkk/resource/mari.png
nonebot_plugin_randomtkk/resource/mark.png
nonebot_plugin_randomtkk/resource/msyh.ttc
nonebot_plugin_randomtkk/resource/nico.png
nonebot_plugin_randomtkk/resource/nozomi.png
nonebot_plugin_randomtkk/resource/ren.png
nonebot_plugin_randomtkk/resource/riko.png
nonebot_plugin_randomtkk/resource/rin.png
nonebot_plugin_randomtkk/resource/ruby.png
nonebot_plugin_randomtkk/resource/sumire.png
nonebot_plugin_randomtkk/resource/tankuku.png
nonebot_plugin_randomtkk/resource/umi.png
nonebot_plugin_randomtkk/resource/yoshiko.png
nonebot_plugin_randomtkk/resource/you.png
nonebot_plugin_randomtkk-0.1.5.post1.dist-info/LICENSE
nonebot_plugin_randomtkk-0.1.5.post1.dist-info/METADATA
nonebot_plugin_randomtkk-0.1.5.post1.dist-info/WHEEL
nonebot_plugin_randomtkk-0.1.5.post1.dist-info/RECORD
